setup.py
deque/__init__.py
deque/datatypes.py
deque/deque_config.py
deque/deque_environment.py
deque/deque_run.py
deque/parsing_service.py
deque/redis_services.py
deque/rest_connect.py
deque/util.py
dequeapp.egg-info/PKG-INFO
dequeapp.egg-info/SOURCES.txt
dequeapp.egg-info/dependency_links.txt
dequeapp.egg-info/requires.txt
dequeapp.egg-info/top_level.txt