Metadata-Version: 2.1
Name: dequeapp
Version: 0.548
Summary: Python Package for Deque tools
Home-page: https://github.com/rijupahwa/deque
Author: The Deque Team
Author-email: team@deque.app
License: UNKNOWN
Keywords: deque client for experiment tracking,sweep and other deep learning tooling
Platform: UNKNOWN
